{
  "/_not-found/page": "app/_not-found/page.js",
  "/blog/page": "app/blog/page.js",
  "/about/page": "app/about/page.js",
  "/contact/page": "app/contact/page.js",
  "/page": "app/page.js",
  "/playground/page": "app/playground/page.js",
  "/privacy/page": "app/privacy/page.js",
  "/signup/page": "app/signup/page.js",
  "/terms/page": "app/terms/page.js",
  "/sitemap.xml/route": "app/sitemap.xml/route.js",
  "/blog/stop-chatbot-prompt-injection/page": "app/blog/stop-chatbot-prompt-injection/page.js",
  "/blog/prevent-ai-email-attacks/page": "app/blog/prevent-ai-email-attacks/page.js"
}